glycowork/__init__.py
glycowork/_modidx.py
glycowork/_nbdev.py
glycowork/core.py
glycowork/examples.py
glycowork/glycan_data.py
glycowork/ml.py
glycowork/motif.py
glycowork/network.py
glycowork/glycan_data/Ab_array_Arabidopsis_thaliana _roots_PMID37608048.csv
glycowork/glycan_data/__init__.py
glycowork/glycan_data/data_entry.py
glycowork/glycan_data/glycan_motifs.csv
glycowork/glycan_data/glycomics_HIV_gagtransfection_N_PMID35112714.csv
glycowork/glycan_data/glycomics_HIV_gagtransfection_O_PMID35112714.csv
glycowork/glycan_data/glycomics_cell_lines_gRNA_GPST000463.csv
glycowork/glycan_data/glycomics_human_brain_GSL_PMID38343116.csv
glycowork/glycan_data/glycomics_human_brain_GSL_PMID40207879.csv
glycowork/glycan_data/glycomics_human_brain_N_PMID38343116.csv
glycowork/glycan_data/glycomics_human_brain_O_PMID38343116.csv
glycowork/glycan_data/glycomics_human_colorectal_N_PMID26085185.csv
glycowork/glycan_data/glycomics_human_colorectal_O_PMC9254241.csv
glycowork/glycan_data/glycomics_human_colorectal_O_PMID19152289.csv
glycowork/glycan_data/glycomics_human_gastric_O_PMC4816881.csv
glycowork/glycan_data/glycomics_human_gastric_O_PMC5762837.csv
glycowork/glycan_data/glycomics_human_gastric_O_PMC7226152.csv
glycowork/glycan_data/glycomics_human_gastric_O_PMID28461410.csv
glycowork/glycan_data/glycomics_human_leukemia_N_PMID34646384.csv
glycowork/glycan_data/glycomics_human_leukemia_O_PMID34646384.csv
glycowork/glycan_data/glycomics_human_liver_O_PMC5383776.csv
glycowork/glycan_data/glycomics_human_liver_O_PMC9254241.csv
glycowork/glycan_data/glycomics_human_ovarian_O_PMC4468167.csv
glycowork/glycan_data/glycomics_human_platelets_N_PMID36952551.csv
glycowork/glycan_data/glycomics_human_platelets_O_PMID36952551.csv
glycowork/glycan_data/glycomics_human_prostate_N_PMC8010466.csv
glycowork/glycan_data/glycomics_human_prostate_O_PMC8010466.csv
glycowork/glycan_data/glycomics_human_retina_GSL_PMC5173345.csv
glycowork-1.7.0.dist-info/METADATA
glycowork-1.7.0.dist-info/WHEEL
glycowork-1.7.0.dist-info/top_level.txt
glycowork-1.7.0.dist-info/RECORD
