Metadata-Version: 2.4
Name: glycowork
Version: 1.7.0
Summary: Package for processing and analyzing glycans
Home-page: https://github.com/BojarLab/glycowork
Author: Daniel Bojar
Author-email: Daniel Bojar <daniel.bojar@gu.se>
Project-URL: Homepage, https://github.com/BojarLab/glycowork
Classifier: Programming Language :: Python :: 3
Classifier: Operating System :: OS Independent
Requires-Python: >=3.9
Requires-Dist: numpy
Requires-Dist: matplotlib
Requires-Dist: scikit-learn
Requires-Dist: networkx>=3.0
Requires-Dist: statsmodels
Requires-Dist: scipy
Requires-Dist: seaborn
Requires-Dist: bokeh
Requires-Dist: IPython
Requires-Dist: pandas>=1.3
Requires-Dist: setuptools>=64.0
Requires-Dist: huggingface_hub>=0.16.0
Requires-Dist: drawSvg~=2.0
Requires-Dist: openpyxl
Requires-Dist: glycorender[png]~=0.2.3
Provides-Extra: all
Requires-Dist: torch_geometric; extra == "all"
Requires-Dist: torch; extra == "all"
Requires-Dist: xgboost; extra == "all"
Requires-Dist: glyles~=1.2.3a0; extra == "all"
Requires-Dist: pubchempy; extra == "all"
Requires-Dist: requests; extra == "all"
Requires-Dist: py3Dmol; extra == "all"
Provides-Extra: dev
Requires-Dist: nbdev; extra == "dev"
Requires-Dist: torch_geometric; extra == "dev"
Requires-Dist: torch; extra == "dev"
Requires-Dist: xgboost; extra == "dev"
Requires-Dist: glyles~=1.2.3a0; extra == "dev"
Requires-Dist: pubchempy; extra == "dev"
Requires-Dist: requests; extra == "dev"
Requires-Dist: py3Dmol; extra == "dev"
Requires-Dist: pytest; extra == "dev"
Provides-Extra: ml
Requires-Dist: torch_geometric; extra == "ml"
Requires-Dist: torch; extra == "ml"
Requires-Dist: xgboost; extra == "ml"
Provides-Extra: chem
Requires-Dist: glyles~=1.2.3a0; extra == "chem"
Requires-Dist: pubchempy; extra == "chem"
Requires-Dist: requests; extra == "chem"
Requires-Dist: py3Dmol; extra == "chem"
Dynamic: author
Dynamic: home-page
Dynamic: requires-python
